processtext/__init__.py
processtext/processtext.py
processtext-0.1.7.dist-info/LICENSE
processtext-0.1.7.dist-info/METADATA
processtext-0.1.7.dist-info/WHEEL
processtext-0.1.7.dist-info/top_level.txt
processtext-0.1.7.dist-info/RECORD
