Metadata-Version: 2.1
Name: processtext
Version: 0.1.7
Summary: An open-source python package to process text data
Home-page: https://github.com/U77w41/processtext
Author: Ujjwal Chowdhury
Author-email: <u77w41@gmail.com>
License: MIT
Keywords: python,nlp,text,regex,text processing
Classifier: Programming Language :: Python :: 3.8
Classifier: License :: OSI Approved :: MIT License
Classifier: Operating System :: OS Independent
Requires-Python: >=3.8
License-File: LICENSE
Requires-Dist: nltk
Requires-Dist: autocorrect
